ipyidv.py
ipython_IDV.py
tests/__init__.py
tests/test_sample.py
ipyidv-2.4.9.dist-info/LICENSE
ipyidv-2.4.9.dist-info/METADATA
ipyidv-2.4.9.dist-info/WHEEL
ipyidv-2.4.9.dist-info/top_level.txt
ipyidv-2.4.9.dist-info/RECORD
