Metadata-Version: 2.1
Name: ipyidv
Version: 2.4.9
Summary: This project allows users to use Unidata's IDV with jupyter notebooks 
Home-page: UNKNOWN
Author: Drilsdown team
Author-email: drilsdown@unidata.ucar.edu
License: UNKNOWN
Platform: UNKNOWN
Classifier: Development Status :: 2 - Pre-Alpha
Classifier: Framework :: IPython
Classifier: Programming Language :: Python
Classifier: Programming Language :: Python :: 2
Classifier: Programming Language :: Python :: 2.7
Classifier: Programming Language :: Python :: 3
Classifier: Programming Language :: Python :: 3.4
Classifier: Programming Language :: Python :: 3.5
Classifier: Programming Language :: Python :: 3.6
Classifier: Programming Language :: Python :: 3.7
Requires-Dist: ipython
Requires-Dist: ipywidgets
Requires-Dist: requests
Provides-Extra: addons
Requires-Dist: netcdf4 ; extra == 'addons'
Requires-Dist: xarray ; extra == 'addons'
